Metadata-Version: 1.0
Name: test-distributions-class
Version: 0.1
Summary: Gaussian distributions and Binomial distribution
Home-page: UNKNOWN
Author: Irfan sp
Author-email: UNKNOWN
License: UNKNOWN
Platform: UNKNOWN
